vietnam_qr_pay/__init__.py
vietnam_qr_pay/crc16.py
vietnam_qr_pay/qr_pay.py
vietnam_qr_pay/constants/__init__.py
vietnam_qr_pay/constants/bank_code.py
vietnam_qr_pay/constants/bank_key.py
vietnam_qr_pay/constants/banks.py
vietnam_qr_pay/constants/qr_pay.py
vietnam_qr_pay-1.0.0.dist-info/licenses/LICENSE
vietnam_qr_pay-1.0.0.dist-info/METADATA
vietnam_qr_pay-1.0.0.dist-info/WHEEL
vietnam_qr_pay-1.0.0.dist-info/top_level.txt
vietnam_qr_pay-1.0.0.dist-info/RECORD
