Metadata-Version: 2.4
Name: vietnam-qr-pay
Version: 1.0.0
Summary: Python library for encoding/decoding Vietnamese bank QR codes (VietQR, VNPayQR)
Author-email: Vietnam QR Pay Contributors <me@bangprovn.com>
License-Expression: MIT
Project-URL: Homepage, https://github.com/bangprovn/vietnam-qr-pay-python
Project-URL: Repository, https://github.com/bangprovn/vietnam-qr-pay-python
Project-URL: Bug Tracker, https://github.com/bangprovn/vietnam-qr-pay-python/issues
Keywords: vietqr,vnpay,qr,vietnam,payment,banking
Classifier: Development Status :: 5 - Production/Stable
Classifier: Intended Audience :: Developers
Classifier: Programming Language :: Python :: 3
Classifier: Programming Language :: Python :: 3.8
Classifier: Programming Language :: Python :: 3.9
Classifier: Programming Language :: Python :: 3.10
Classifier: Programming Language :: Python :: 3.11
Classifier: Programming Language :: Python :: 3.12
Classifier: Topic :: Software Development :: Libraries :: Python Modules
Classifier: Topic :: Office/Business :: Financial
Requires-Python: >=3.8
License-File: LICENSE
Provides-Extra: examples
Requires-Dist: qrcode[pil]>=7.4.2; extra == "examples"
Dynamic: license-file
